hello.py
llxm-0.0.1.dist-info/METADATA
llxm-0.0.1.dist-info/WHEEL
llxm-0.0.1.dist-info/top_level.txt
llxm-0.0.1.dist-info/RECORD
