Metadata-Version: 2.1
Name: llxm
Version: 0.0.1
Summary: llxm -- the new home of zyx
Requires-Python: >=3.8
